Nimbus/__init__.py
Nimbus/app.py
Nimbus/middleware.py
Nimbus/response.py
nimbus_web_framework-0.1.4.dist-info/METADATA
nimbus_web_framework-0.1.4.dist-info/WHEEL
nimbus_web_framework-0.1.4.dist-info/top_level.txt
nimbus_web_framework-0.1.4.dist-info/RECORD
