Metadata-Version: 2.1
Name: nimbus-web-framework
Version: 0.1.4
Summary: A lightweight Python web framework built for learning purposes.
Home-page: https://github.com/yourusername/nimbus-web-framework
Author: Abulqosim Rafiqov
Author-email: rafiqovbulqosim@gmail.com
License: MIT
Classifier: License :: OSI Approved :: MIT License
Classifier: Programming Language :: Python
Classifier: Programming Language :: Python :: 3
Classifier: Programming Language :: Python :: 3.8
Classifier: Programming Language :: Python :: Implementation :: CPython
Classifier: Programming Language :: Python :: Implementation :: PyPy
Requires-Python: >=3.8.0
Requires-Dist: Jinja2>=3.1.5
Requires-Dist: parse>=1.20.2
Requires-Dist: requests>=2.32.3
Requires-Dist: requests-wsgi-adapter>=0.4.1
Requires-Dist: WebOb>=1.8.9
Requires-Dist: whitenoise>=6.7.0
